jays/__init__.py
jays/where.py
jays-2023.1.0a1.dist-info/METADATA
jays-2023.1.0a1.dist-info/WHEEL
jays-2023.1.0a1.dist-info/RECORD
